knowlang/api/README.md
knowlang/api/__init__.py
knowlang/api/base.py
knowlang/api/config.py
knowlang/api/main.py
knowlang/api/main.spec
knowlang/api/chat/router.py
knowlang/api/health/router.py
knowlang/api/parse/router.py
knowlang/assets/DomainAssetChunk.jpg
knowlang/assets/README.md
knowlang/assets/__main__.py
knowlang/assets/config.py
knowlang/assets/models.py
knowlang/assets/processor.py
knowlang/assets/registry.py
knowlang/assets/codebase/models.py
knowlang/assets/codebase/processor.py
knowlang/chat_bot/__init__.py
knowlang/chat_bot/chat_graph.py
knowlang/chat_bot/chat_interface.py
knowlang/chat_bot/feedback.py
knowlang/chat_bot/nodes/base.py
knowlang/cli/__init__.py
knowlang/cli/__main__.py
knowlang/cli/argparser.py
knowlang/cli/types.py
knowlang/cli/commands/chat.py
knowlang/cli/commands/parse.py
knowlang/cli/commands/mcp/serve.py
knowlang/cli/display/formatters.py
knowlang/configs/__init__.py
knowlang/configs/base.py
knowlang/configs/chat_config.py
knowlang/configs/config.py
knowlang/configs/defaults.py
knowlang/configs/llm_config.py
knowlang/configs/logging_config.py
knowlang/configs/retrieval_config.py
knowlang/configs/server_config.py
knowlang/configs/state_store_config.py
knowlang/core/types.py
knowlang/database/config.py
knowlang/database/db.py
knowlang/mcp/README.md
knowlang/mcp/claude_desktop_config.json
knowlang/mcp/common.py
knowlang/mcp/knowlang_tools.png
knowlang/mcp/server.py
knowlang/mcp/tools/vector_search.py
knowlang/models/__init__.py
knowlang/models/embedding_providers.py
knowlang/models/embeddings.py
knowlang/models/types.py
knowlang/models/utils.py
knowlang/models/nomic_ai/model.py
knowlang/parser/factory.py
knowlang/parser/base/parser.py
knowlang/parser/base/provider.py
knowlang/parser/languages/cpp/parser.py
knowlang/parser/languages/csharp/__init__.py
knowlang/parser/languages/csharp/parser.py
knowlang/parser/languages/python/parser.py
knowlang/parser/languages/ts/parser.py
knowlang/parser/languages/unity_asset/parser.py
knowlang-0.3.0.dist-info/METADATA
knowlang-0.3.0.dist-info/WHEEL
knowlang-0.3.0.dist-info/entry_points.txt
knowlang-0.3.0.dist-info/licenses/LICENSE
knowlang-0.3.0.dist-info/RECORD
