Metadata-Version: 2.4
Name: knowlang
Version: 0.3.0
Summary: AI-powered code understanding assistant that helps developers explore and understand complex codebases through semantic search and intelligent Q&A
Project-URL: Homepage, https://knowlang.dev
Project-URL: Repository, https://github.com/knowlangorg/know-lang
Author-email: gabhyun kim <kimgb415@gmail.com>, mukhtar kussaiynbekov <mukhtarkussaiynbekov@gmail.com>, kolbe yang <kyanghasglasses@gmail.com>
License-Expression: Apache-2.0
License-File: LICENSE
Classifier: Development Status :: 4 - Beta
Classifier: Intended Audience :: Developers
Classifier: License :: OSI Approved :: Apache Software License
Classifier: Operating System :: OS Independent
Classifier: Programming Language :: Python :: 3
Classifier: Programming Language :: Python :: 3.10
Classifier: Programming Language :: Python :: 3.11
Classifier: Programming Language :: Python :: 3.12
Classifier: Topic :: Scientific/Engineering :: Artificial Intelligence
Classifier: Topic :: Software Development :: Documentation
Classifier: Topic :: Software Development :: Libraries :: Python Modules
Requires-Python: <3.13,>=3.10
Requires-Dist: aiofiles>=24.1.0
Requires-Dist: aiohttp>=3.11.18
Requires-Dist: gitpython<4.0.0,>=3.1.44
Requires-Dist: pydantic-ai>=0.1.0
Requires-Dist: pydantic-settings<3.0.0,>=2.7.1
Requires-Dist: sqlalchemy[asyncio]<3.0.0,>=2.0.38
Requires-Dist: tree-sitter<0.25.0,>=0.24.0
